[
  {
    "id": "021 bleach cleanser(Clone)-19400",
    "pickRotation": [
      [
        -0.06912485,
        0.166359633,
        0.98363924
      ],
      [
        -0.997557,
        -0.021502275,
        -0.0664663
      ],
      [
        0.0100931721,
        -0.985830665,
        0.16743955
      ]
    ],
    "pickTranslation": [
      -0.009850996,
      0.0124277445,
      0.205580086
    ],
    "placeRotation": [
      [
        -0.8534158,
        0.510004759,
        -0.107595168
      ],
      [
        -0.50493145,
        -0.8601413,
        -0.07211925
      ],
      [
        -0.1293282,
        -0.007219519,
        0.991575539
      ]
    ],
    "placeTranslation": [
      0.9747881,
      0.447432518,
      -0.369393915
    ]
  },
  {
    "id": "021 bleach cleanser(Clone)-19464",
    "pickRotation": [
      [
        0.04304573,
        0.07668471,
        0.996125758
      ],
      [
        -0.9963467,
        0.07690381,
        0.0371349938
      ],
      [
        -0.07375818,
        -0.994085133,
        0.07971494
      ]
    ],
    "pickTranslation": [
      -0.00318922615,
      0.00302773761,
      0.218160823
    ],
    "placeRotation": [
      [
        -0.984381437,
        0.1366174,
        -0.111035712
      ],
      [
        -0.168754265,
        -0.911920369,
        0.3740632
      ],
      [
        -0.0501521826,
        0.3869586,
        0.9207322
      ]
    ],
    "placeTranslation": [
      0.947497547,
      0.266355366,
      0.631163239
    ]
  },
  {
    "id": "004 sugar box(Clone)-19170",
    "pickRotation": [
      [
        -0.984233737,
        -0.145451054,
        0.100637637
      ],
      [
        -0.12421871,
        0.163389459,
        -0.9787102
      ],
      [
        0.1259113,
        -0.975780666,
        -0.178881168
      ]
    ],
    "pickTranslation": [
      0.008733195,
      -0.0194889,
      0.168216884
    ],
    "placeRotation": [
      [
        0.6479925,
        -0.06268202,
        0.759063065
      ],
      [
        -0.746324956,
        -0.2511498,
        0.616378844
      ],
      [
        0.152002662,
        -0.9659165,
        -0.209524348
      ]
    ],
    "placeTranslation": [
      -0.665541351,
      0.215488836,
      -0.8366215
    ]
  },
  {
    "id": "008 pudding box(Clone)-19118",
    "pickRotation": [
      [
        0.212726176,
        -0.6529227,
        0.7269385
      ],
      [
        0.0475881547,
        -0.736160636,
        -0.675131738
      ],
      [
        0.9759523,
        0.178211853,
        -0.125529259
      ]
    ],
    "pickTranslation": [
      0.00683177,
      0.0358646736,
      0.0157454647
    ],
    "placeRotation": [
      [
        -0.109978721,
        -0.163248345,
        -0.980435967
      ],
      [
        0.5998546,
        0.7756213,
        -0.196433172
      ],
      [
        0.792514443,
        -0.6097225,
        0.012623433
      ]
    ],
    "placeTranslation": [
      -0.708169937,
      0.66591084,
      0.9346364
    ]
  },
  {
    "id": "008 pudding box(Clone)-19412",
    "pickRotation": [
      [
        0.08407963,
        -0.56598,
        0.8201203
      ],
      [
        -0.0430929326,
        -0.824329853,
        -0.5644672
      ],
      [
        0.9955268,
        0.0121188052,
        -0.09369909
      ]
    ],
    "pickTranslation": [
      0.0017116922,
      0.0460875072,
      0.009529375
    ],
    "placeRotation": [
      [
        -0.298636466,
        -0.382002056,
        -0.8745803
      ],
      [
        0.4017624,
        0.7809198,
        -0.478279531
      ],
      [
        0.8656808,
        -0.494205147,
        -0.07973706
      ]
    ],
    "placeTranslation": [
      -0.00315933954,
      0.5696621,
      0.8724929
    ]
  },
  {
    "id": "025 mug(Clone)-19186",
    "pickRotation": [
      [
        -0.118137971,
        0.08908803,
        -0.9889928
      ],
      [
        0.9803206,
        0.169098139,
        -0.101869762
      ],
      [
        0.158161461,
        -0.981564641,
        -0.107311741
      ]
    ],
    "pickTranslation": [
      0.0163359456,
      0.0226289332,
      0.07070336
    ],
    "placeRotation": [
      [
        -0.950343132,
        0.304194033,
        0.06568045
      ],
      [
        0.0398260243,
        -0.09043764,
        0.9951055
      ],
      [
        0.308645129,
        0.948307455,
        0.07383196
      ]
    ],
    "placeTranslation": [
      0.8799463,
      0.419077337,
      0.499798745
    ]
  },
  {
    "id": "010 potted meat can(Clone)-19146",
    "pickRotation": [
      [
        0.139035389,
        0.05752104,
        -0.988615453
      ],
      [
        0.96408236,
        0.220277593,
        0.148401648
      ],
      [
        0.226306051,
        -0.973739743,
        -0.0248286389
      ]
    ],
    "pickTranslation": [
      0.03265741,
      -0.0251156278,
      0.0782021061
    ],
    "placeRotation": [
      [
        0.9873936,
        -0.140170023,
        -0.07352703
      ],
      [
        -0.07707477,
        -0.8315112,
        0.550135136
      ],
      [
        -0.138250992,
        -0.537532866,
        -0.8318324
      ]
    ],
    "placeTranslation": [
      -0.348491579,
      0.288415283,
      -0.7749692
    ]
  },
  {
    "id": "100 half egg carton(Clone)-19134",
    "pickRotation": [
      [
        0.009829354,
        -0.116423875,
        0.993150949
      ],
      [
        0.179167509,
        -0.976921,
        -0.116294533
      ],
      [
        0.9837695,
        0.179083481,
        0.0112568736
      ]
    ],
    "pickTranslation": [
      -0.06936413,
      0.03402634,
      -0.006251037
    ],
    "placeRotation": [
      [
        0.007544176,
        0.07893197,
        -0.9968514
      ],
      [
        -0.151532292,
        0.9854577,
        0.07688301
      ],
      [
        0.988423467,
        0.150475159,
        0.01939521
      ]
    ],
    "placeTranslation": [
      0.167602256,
      0.594782054,
      -0.5658656
    ]
  },
  {
    "id": "100 half egg carton(Clone)-19452",
    "pickRotation": [
      [
        -0.0409516767,
        -0.0213617664,
        0.9989328
      ],
      [
        0.127353489,
        -0.991728544,
        -0.0159867965
      ],
      [
        0.9910117,
        0.126562878,
        0.04333344
      ]
    ],
    "pickTranslation": [
      -0.06357134,
      0.0332727171,
      -0.00279893749
    ],
    "placeRotation": [
      [
        -0.0280302353,
        0.33472693,
        -0.941898167
      ],
      [
        -0.04016765,
        0.941130161,
        0.335649371
      ],
      [
        0.9987997,
        0.0472421646,
        -0.0129349064
      ]
    ],
    "placeTranslation": [
      0.1612489,
      0.8376477,
      -0.62930584
    ]
  },
  {
    "id": "101 bread(Clone)-19106",
    "pickRotation": [
      [
        -0.9790211,
        -0.200998247,
        -0.0334276631
      ],
      [
        0.203678817,
        -0.969976842,
        -0.132890463
      ],
      [
        -0.00571331149,
        -0.136911079,
        0.99056685
      ]
    ],
    "pickTranslation": [
      -0.000800832,
      0.0294708479,
      -0.001455529
    ],
    "placeRotation": [
      [
        -0.0508342423,
        -0.0690560043,
        -0.9963168
      ],
      [
        0.495578855,
        0.864374459,
        -0.08519642
      ],
      [
        0.8670741,
        -0.498084426,
        -0.009717125
      ]
    ],
    "placeTranslation": [
      -0.8136407,
      0.5562055,
      -0.2001839
    ]
  },
  {
    "id": "018 plum(Clone)-19428",
    "pickRotation": [
      [
        -0.800389,
        0.5937651,
        0.08258699
      ],
      [
        -0.566049933,
        -0.7939104,
        0.222022012
      ],
      [
        0.197395578,
        0.1309556,
        0.971537769
      ]
    ],
    "pickTranslation": [
      0.0149820177,
      0.0324281119,
      0.0177674983
    ],
    "placeRotation": [
      [
        0.902088344,
        0.248025432,
        -0.353157163
      ],
      [
        -0.350555241,
        0.8984243,
        -0.2644707
      ],
      [
        0.251689523,
        0.362377018,
        0.89740473
      ]
    ],
    "placeTranslation": [
      0.7858365,
      0.7494419,
      0.5344134
    ]
  },
  {
    "id": "012 strawberry(Clone)-19440",
    "pickRotation": [
      [
        -0.676914334,
        -0.270775348,
        -0.68444705
      ],
      [
        0.164547548,
        -0.962011933,
        0.217846721
      ],
      [
        -0.7174337,
        0.0348394923,
        0.695755064
      ]
    ],
    "pickTranslation": [
      0.00117871445,
      0.0187836047,
      0.0232259
    ],
    "placeRotation": [
      [
        0.4963631,
        -0.235157222,
        0.835658252
      ],
      [
        0.362950951,
        0.930657,
        0.04630513
      ],
      [
        -0.7886002,
        0.2803188,
        0.5472943
      ]
    ],
    "placeTranslation": [
      0.653596342,
      0.7897927,
      0.448191583
    ]
  },
  {
    "id": "058 golf ball(Clone)-19158",
    "pickRotation": [
      [
        -0.9781584,
        -0.0292846449,
        -0.205787882
      ],
      [
        0.195988163,
        -0.459745765,
        -0.866153836
      ],
      [
        -0.06924511,
        -0.887567639,
        0.4554436
      ]
    ],
    "pickTranslation": [
      0.006736991,
      -0.0309581887,
      0.0230988823
    ],
    "placeRotation": [
      [
        0.9958168,
        -0.0614779629,
        -0.06759606
      ],
      [
        0.0880134553,
        0.4466754,
        0.890356541
      ],
      [
        -0.0245438162,
        -0.8925814,
        0.450217783
      ]
    ],
    "placeTranslation": [
      1.08841193,
      0.922501564,
      0.205209643
    ]
  }
]