[
  {
    "id": "004 sugar box(Clone)-3628",
    "pickRotation": [
      [
        -0.977812648,
        0.0118478863,
        0.209146008
      ],
      [
        -0.1526843,
        -0.723866761,
        -0.6728331
      ],
      [
        0.1434222,
        -0.689838,
        0.7096151
      ]
    ],
    "pickTranslation": [
      0.008519185,
      0.03528207,
      0.1173694
    ],
    "placeRotation": [
      [
        -0.0302238446,
        0.02735086,
        0.9991689
      ],
      [
        -0.9864326,
        0.160557851,
        -0.03423363
      ],
      [
        -0.161360726,
        -0.9866475,
        0.0221271031
      ]
    ],
    "placeTranslation": [
      -0.578792155,
      0.273446351,
      -0.970476747
    ]
  },
  {
    "id": "008 pudding box(Clone)-3800",
    "pickRotation": [
      [
        0.20947814,
        -0.447219342,
        0.869548
      ],
      [
        -0.146918073,
        -0.8935783,
        -0.424185127
      ],
      [
        0.966712952,
        -0.0388948061,
        -0.2528897
      ]
    ],
    "pickTranslation": [
      0.022133749,
      0.0597885549,
      0.016692251
    ],
    "placeRotation": [
      [
        0.903227,
        -0.428352058,
        -0.0263724513
      ],
      [
        0.141072,
        0.238306388,
        0.9608896
      ],
      [
        -0.4053143,
        -0.8716218,
        0.27567324
      ]
    ],
    "placeTranslation": [
      -0.752815,
      0.287978441,
      -0.410439819
    ]
  },
  {
    "id": "002 masterchef can(Clone)-3580",
    "pickRotation": [
      [
        -0.9361431,
        -0.109311059,
        -0.3341963
      ],
      [
        0.320230871,
        0.127485573,
        -0.9387223
      ],
      [
        0.14521794,
        -0.9857984,
        -0.08433997
      ]
    ],
    "pickTranslation": [
      0.0160365049,
      -0.0245110244,
      0.142099872
    ],
    "placeRotation": [
      [
        0.9657478,
        -0.259072274,
        0.0145864161
      ],
      [
        -0.04176618,
        -0.09971996,
        0.9941386
      ],
      [
        -0.2560992,
        -0.96069634,
        -0.107124783
      ]
    ],
    "placeTranslation": [
      -0.770501852,
      0.26279366,
      0.165677786
    ]
  },
  {
    "id": "005 tomato soup can(Clone)-3764",
    "pickRotation": [
      [
        -0.8315117,
        -0.0835265443,
        -0.5491919
      ],
      [
        0.5502624,
        0.0116873365,
        -0.834910035
      ],
      [
        0.07615574,
        -0.996437,
        0.03624336
      ]
    ],
    "pickTranslation": [
      0.01008856,
      0.0799438655,
      0.101644568
    ],
    "placeRotation": [
      [
        0.9505566,
        -0.309544325,
        -0.0249904823
      ],
      [
        0.00589851057,
        -0.06246079,
        0.99803
      ],
      [
        -0.310495436,
        -0.9488314,
        -0.057546664
      ]
    ],
    "placeTranslation": [
      -1.279064,
      0.5097758,
      -0.4918076
    ]
  },
  {
    "id": "017 orange(Clone)-3544",
    "pickRotation": [
      [
        0.249561951,
        0.349697948,
        -0.9030117
      ],
      [
        -0.780726,
        -0.479011148,
        -0.401266932
      ],
      [
        -0.5728749,
        0.8051457,
        0.153475329
      ]
    ],
    "pickTranslation": [
      0.007909639,
      0.002999275,
      -0.005703261
    ],
    "placeRotation": [
      [
        0.09992129,
        0.611281753,
        0.785079837
      ],
      [
        -0.491134554,
        0.716508448,
        -0.495381147
      ],
      [
        -0.8653338,
        -0.3360807,
        0.371816039
      ]
    ],
    "placeTranslation": [
      -0.136795491,
      0.466414571,
      0.4948211
    ]
  },
  {
    "id": "017 orange(Clone)-3680",
    "pickRotation": [
      [
        -0.0589635335,
        0.19555895,
        -0.9789178
      ],
      [
        -0.8392247,
        -0.54073894,
        -0.0574743748
      ],
      [
        -0.540578544,
        0.81814307,
        0.196001783
      ]
    ],
    "pickTranslation": [
      0.00184091693,
      -0.00826798752,
      0.0113298967
    ],
    "placeRotation": [
      [
        0.3086125,
        0.646060646,
        0.698114634
      ],
      [
        -0.39904958,
        0.754167259,
        -0.5215277
      ],
      [
        -0.8634337,
        -0.117632367,
        0.490555674
      ]
    ],
    "placeTranslation": [
      -0.4477382,
      0.727318943,
      0.5468171
    ]
  },
  {
    "id": "013 apple(Clone)-3644",
    "pickRotation": [
      [
        -0.497053951,
        -0.15703623,
        -0.8533915
      ],
      [
        0.831705451,
        0.194178551,
        -0.5201546
      ],
      [
        0.247393429,
        -0.968315244,
        0.03409068
      ]
    ],
    "pickTranslation": [
      0.00262013287,
      -0.00310540246,
      0.06570087
    ],
    "placeRotation": [
      [
        0.5468696,
        -0.7738326,
        -0.31955713
      ],
      [
        0.04260455,
        -0.3554725,
        0.9337152
      ],
      [
        -0.836133063,
        -0.524235,
        -0.1614283
      ]
    ],
    "placeTranslation": [
      -0.149506956,
      0.07667086,
      0.07474628
    ]
  },
  {
    "id": "012 strawberry(Clone)-3532",
    "pickRotation": [
      [
        0.585929155,
        -0.4777108,
        0.654583335
      ],
      [
        -0.243375346,
        -0.8742121,
        -0.4201449
      ],
      [
        0.7729524,
        0.08686571,
        -0.628489435
      ]
    ],
    "pickTranslation": [
      0.01855607,
      0.037396688,
      0.0260297246
    ],
    "placeRotation": [
      [
        -0.675856948,
        0.266503066,
        -0.6871634
      ],
      [
        0.5613507,
        0.7902901,
        -0.245615587
      ],
      [
        0.477601081,
        -0.551740646,
        -0.683724761
      ]
    ],
    "placeTranslation": [
      -0.4805111,
      0.4459373,
      0.397165567
    ]
  },
  {
    "id": "015 peach(Clone)-3692",
    "pickRotation": [
      [
        0.4047813,
        0.128530174,
        0.905335367
      ],
      [
        -0.9067774,
        -0.0712635741,
        0.415543318
      ],
      [
        0.11792729,
        -0.9891418,
        0.0877020955
      ]
    ],
    "pickTranslation": [
      0.01350493,
      0.007766937,
      0.0504354
    ],
    "placeRotation": [
      [
        -0.5964987,
        0.802059054,
        -0.0298425779
      ],
      [
        0.1397405,
        0.140396476,
        0.9801844
      ],
      [
        0.790355563,
        0.58050853,
        -0.195826441
      ]
    ],
    "placeTranslation": [
      -0.119699746,
      0.1470925,
      -0.5097599
    ]
  },
  {
    "id": "015 peach(Clone)-3668",
    "pickRotation": [
      [
        -0.237031832,
        0.0633398741,
        0.969434857
      ],
      [
        -0.9557557,
        -0.19413586,
        -0.221002966
      ],
      [
        0.174203768,
        -0.9789277,
        0.106553823
      ]
    ],
    "pickTranslation": [
      0.0209414549,
      0.00413137674,
      0.03902019
    ],
    "placeRotation": [
      [
        0.490878761,
        0.806641757,
        0.329191566
      ],
      [
        0.07153093,
        -0.4138873,
        0.90751344
      ],
      [
        0.868286431,
        -0.421931684,
        -0.2608683
      ]
    ],
    "placeTranslation": [
      0.147411212,
      0.139818266,
      -0.8683227
    ]
  },
  {
    "id": "015 peach(Clone)-3704",
    "pickRotation": [
      [
        0.9693332,
        0.008957666,
        0.245586887
      ],
      [
        -0.2455195,
        0.07858933,
        0.966200769
      ],
      [
        -0.0106455926,
        -0.996866763,
        0.07837853
      ]
    ],
    "pickTranslation": [
      0.0179606322,
      0.00856932,
      0.06630794
    ],
    "placeRotation": [
      [
        -0.7603878,
        0.5585058,
        0.331484
      ],
      [
        0.402848929,
        0.00524654053,
        0.915251434
      ],
      [
        0.509434044,
        0.829484,
        -0.228982881
      ]
    ],
    "placeTranslation": [
      0.231963158,
      -0.0216181427,
      -0.228919461
    ]
  },
  {
    "id": "015 peach(Clone)-3568",
    "pickRotation": [
      [
        -0.905222952,
        -0.169874772,
        0.3895049
      ],
      [
        -0.36982283,
        -0.136513248,
        -0.9190186
      ],
      [
        0.209290653,
        -0.9759645,
        0.06075135
      ]
    ],
    "pickTranslation": [
      0.0199261047,
      0.01177389,
      0.0588158667
    ],
    "placeRotation": [
      [
        0.9493291,
        0.311208665,
        0.043857757
      ],
      [
        0.0140155805,
        -0.181330755,
        0.983322263
      ],
      [
        0.3139712,
        -0.9328817,
        -0.176504329
      ]
    ],
    "placeTranslation": [
      -0.00740397163,
      0.3584205,
      -0.5454516
    ]
  },
  {
    "id": "016 pear(Clone)-3728",
    "pickRotation": [
      [
        -0.9756371,
        0.0259675868,
        0.217848435
      ],
      [
        -0.219381437,
        -0.124571577,
        -0.9676537
      ],
      [
        0.00201010844,
        -0.991870761,
        0.127233461
      ]
    ],
    "pickTranslation": [
      0.0283613466,
      0.0054455013,
      0.07317282
    ],
    "placeRotation": [
      [
        0.6532372,
        0.74370724,
        -0.142058685
      ],
      [
        0.2036869,
        0.008094533,
        0.9790026
      ],
      [
        0.7292412,
        -0.668456435,
        -0.146195754
      ]
    ],
    "placeTranslation": [
      0.2963003,
      -0.0411036871,
      0.21905449
    ]
  },
  {
    "id": "016 pear(Clone)-3556",
    "pickRotation": [
      [
        -0.200735852,
        0.2205212,
        -0.954502761
      ],
      [
        0.9671782,
        0.199559659,
        -0.157296777
      ],
      [
        0.155792966,
        -0.954749346,
        -0.2533421
      ]
    ],
    "pickTranslation": [
      0.0157318264,
      -0.003862653,
      0.06270691
    ],
    "placeRotation": [
      [
        -0.243118644,
        -0.968237162,
        0.0583964363
      ],
      [
        -0.6108834,
        0.19959721,
        0.7661478
      ],
      [
        -0.7534685,
        0.1505914,
        -0.6400058
      ]
    ],
    "placeTranslation": [
      -0.231095344,
      0.5233155,
      0.5337314
    ]
  },
  {
    "id": "014 lemon(Clone)-3656",
    "pickRotation": [
      [
        -0.4352018,
        -0.7216135,
        0.5383989
      ],
      [
        0.6169326,
        -0.674556732,
        -0.405422568
      ],
      [
        0.655739,
        0.155715212,
        0.7387551
      ]
    ],
    "pickTranslation": [
      0.02569643,
      0.0469624251,
      0.02244523
    ],
    "placeRotation": [
      [
        0.446990848,
        -0.0144785671,
        -0.894421339
      ],
      [
        0.677803636,
        0.6579842,
        0.328084
      ],
      [
        0.5837649,
        -0.752892554,
        0.303926528
      ]
    ],
    "placeTranslation": [
      -0.19601509,
      0.3942281,
      -0.495218515
    ]
  },
  {
    "id": "012 strawberry(Clone)-3752",
    "pickRotation": [
      [
        0.8436258,
        -0.523803055,
        0.118008114
      ],
      [
        -0.535173,
        -0.8380762,
        0.105915651
      ],
      [
        0.04342085,
        -0.152507931,
        -0.98734796
      ]
    ],
    "pickTranslation": [
      0.0280251428,
      0.0375868268,
      0.02754487
    ],
    "placeRotation": [
      [
        -0.8318277,
        0.5549134,
        0.0115664154
      ],
      [
        0.5460473,
        0.82191664,
        -0.162128091
      ],
      [
        -0.09947368,
        -0.128546834,
        -0.9867019
      ]
    ],
    "placeTranslation": [
      -0.345238537,
      0.5057733,
      -0.359514415
    ]
  },
  {
    "id": "012 strawberry(Clone)-3716",
    "pickRotation": [
      [
        -0.6050093,
        -0.608144,
        -0.513930559
      ],
      [
        0.317876458,
        -0.7762793,
        0.5443758
      ],
      [
        -0.7300125,
        0.165985987,
        0.662970841
      ]
    ],
    "pickTranslation": [
      0.0247693937,
      0.0263213888,
      0.00876770448
    ],
    "placeRotation": [
      [
        0.537365,
        -0.304593921,
        0.7864232
      ],
      [
        0.4424302,
        0.8956932,
        0.0446022
      ],
      [
        -0.717979431,
        0.3239697,
        0.6160757
      ]
    ],
    "placeTranslation": [
      -0.168641508,
      0.6018581,
      0.20603548
    ]
  },
  {
    "id": "006 mustard bottle(Clone)-3740",
    "pickRotation": [
      [
        -0.676918566,
        -0.32934463,
        -0.6582655
      ],
      [
        0.7211974,
        -0.117970422,
        -0.682610631
      ],
      [
        0.14715828,
        -0.936811149,
        0.317378849
      ]
    ],
    "pickTranslation": [
      0.0143679092,
      -0.0277119167,
      0.16686134
    ],
    "placeRotation": [
      [
        0.936189651,
        0.351495326,
        7.989153E-06
      ],
      [
        0.0201044939,
        -0.0535699762,
        0.9983617
      ],
      [
        0.3509199,
        -0.9346557,
        -0.05721829
      ]
    ],
    "placeTranslation": [
      0.788981855,
      0.03080407,
      -0.5940595
    ]
  },
  {
    "id": "021 bleach cleanser(Clone)-3776",
    "pickRotation": [
      [
        0.6311705,
        0.264606357,
        0.729114056
      ],
      [
        -0.7651288,
        0.0581418164,
        0.6412468
      ],
      [
        0.127285957,
        -0.9626022,
        0.239155352
      ]
    ],
    "pickTranslation": [
      0.0160924345,
      0.0159520954,
      0.2424404
    ],
    "placeRotation": [
      [
        -0.9918272,
        -0.0144096212,
        -0.126771837
      ],
      [
        -0.1271316,
        0.0276326817,
        0.991500854
      ],
      [
        -0.0107840952,
        0.9995143,
        -0.0292387623
      ]
    ],
    "placeTranslation": [
      0.7496229,
      0.0584521,
      0.684405863
    ]
  },
  {
    "id": "103 toothpaste(Clone)-3592",
    "pickRotation": [
      [
        -0.09850681,
        -0.09087115,
        -0.9909787
      ],
      [
        -0.923283935,
        -0.3631825,
        0.125080958
      ],
      [
        -0.371272355,
        0.927276,
        -0.0481239222
      ]
    ],
    "pickTranslation": [
      0.08756094,
      0.0264379345,
      -0.028783951
    ],
    "placeRotation": [
      [
        0.105888553,
        0.9350402,
        0.338359982
      ],
      [
        0.9941615,
        -0.106649004,
        -0.0164003372
      ],
      [
        0.02075078,
        0.338121057,
        -0.940873861
      ]
    ],
    "placeTranslation": [
      1.02763867,
      0.9457113,
      -0.729882836
    ]
  },
  {
    "id": "058 golf ball(Clone)-3520",
    "pickRotation": [
      [
        -0.937249839,
        -0.142362133,
        -0.318269879
      ],
      [
        0.345544428,
        -0.5010038,
        -0.7934697
      ],
      [
        -0.0464943834,
        -0.853655756,
        0.518758237
      ]
    ],
    "pickTranslation": [
      0.008177628,
      -0.03161542,
      0.0152749568
    ],
    "placeRotation": [
      [
        0.886849344,
        -0.375873655,
        0.268732816
      ],
      [
        -0.311641455,
        -0.05717848,
        0.948477864
      ],
      [
        -0.341142118,
        -0.9249052,
        -0.167846516
      ]
    ],
    "placeTranslation": [
      0.9990008,
      0.967049837,
      -0.284094423
    ]
  },
  {
    "id": "101 bread(Clone)-3788",
    "pickRotation": [
      [
        -0.9831663,
        -0.165580466,
        -0.07724738
      ],
      [
        0.151185885,
        -0.9746466,
        0.164944917
      ],
      [
        -0.102600552,
        0.150489569,
        0.983273149
      ]
    ],
    "pickTranslation": [
      0.00579192443,
      0.04495136,
      -0.04989659
    ],
    "placeRotation": [
      [
        0.08923657,
        -0.09673494,
        -0.9913018
      ],
      [
        0.341462284,
        0.937927663,
        -0.060788203
      ],
      [
        0.935649633,
        -0.333067626,
        0.116728783
      ]
    ],
    "placeTranslation": [
      0.134777218,
      0.788717568,
      -0.129068092
    ]
  }
]