[
  {
    "id": "003 cracker box(Clone)-6540",
    "pickRotation": [
      [
        -0.06751493,
        0.716302037,
        0.69451654
      ],
      [
        -0.997394741,
        -0.03072933,
        -0.06526491
      ],
      [
        -0.0254073627,
        -0.697113454,
        0.716510534
      ]
    ],
    "pickTranslation": [
      -0.0298691541,
      0.0403861143,
      0.146774262
    ],
    "placeRotation": [
      [
        0.0380384065,
        0.999269,
        0.00380128413
      ],
      [
        0.0163719114,
        -0.00442673452,
        0.9998562
      ],
      [
        0.9991421,
        -0.0379707031,
        -0.01652833
      ]
    ],
    "placeTranslation": [
      0.748178363,
      0.0126129948,
      -0.150626034
    ]
  },
  {
    "id": "004 sugar box(Clone)-6746",
    "pickRotation": [
      [
        -0.280293256,
        0.711789548,
        0.644042969
      ],
      [
        -0.958316147,
        -0.168793663,
        -0.230518743
      ],
      [
        -0.05537045,
        -0.681809664,
        0.7294311
      ]
    ],
    "pickTranslation": [
      -0.0189685822,
      0.0205670446,
      0.131302655
    ],
    "placeRotation": [
      [
        0.99801755,
        0.0550493263,
        -0.03050418
      ],
      [
        0.03176729,
        -0.0222176015,
        0.9992483
      ],
      [
        0.0543302149,
        -0.9982364,
        -0.0239223242
      ]
    ],
    "placeTranslation": [
      0.806923747,
      -0.007718528,
      0.687055647
    ]
  },
  {
    "id": "010 potted meat can(Clone)-6798",
    "pickRotation": [
      [
        -0.983564854,
        -0.03886334,
        -0.17632322
      ],
      [
        0.168803319,
        -0.544488251,
        -0.821606934
      ],
      [
        -0.06407554,
        -0.8378676,
        0.5420998
      ]
    ],
    "pickTranslation": [
      0.0570845753,
      -0.0006243287,
      0.0904252753
    ],
    "placeRotation": [
      [
        0.9966412,
        -0.030658,
        -0.0759367943
      ],
      [
        0.07456612,
        -0.0436182,
        0.996261656
      ],
      [
        -0.03385564,
        -0.9985778,
        -0.0411856472
      ]
    ],
    "placeTranslation": [
      -0.7079597,
      0.0130771529,
      -0.745796561
    ]
  },
  {
    "id": "008 pudding box(Clone)-6706",
    "pickRotation": [
      [
        0.2618094,
        -0.338487655,
        0.9038152
      ],
      [
        -0.125908032,
        -0.9404556,
        -0.315737873
      ],
      [
        0.95687145,
        -0.0311344452,
        -0.288838446
      ]
    ],
    "pickTranslation": [
      -0.0186353736,
      0.06965285,
      0.0180763137
    ],
    "placeRotation": [
      [
        0.0450852327,
        0.06241745,
        -0.9970313
      ],
      [
        0.403540552,
        0.9118552,
        0.07533304
      ],
      [
        0.9138503,
        -0.40573895,
        0.0159232337
      ]
    ],
    "placeTranslation": [
      -0.640813768,
      0.158998862,
      0.280493051
    ]
  },
  {
    "id": "100 half egg carton(Clone)-6722",
    "pickRotation": [
      [
        0.950995564,
        0.285481781,
        0.118775122
      ],
      [
        0.272121936,
        -0.9551338,
        0.116914555
      ],
      [
        0.146823123,
        -0.07886391,
        -0.9860139
      ]
    ],
    "pickTranslation": [
      -0.104133844,
      0.0298107229,
      0.0186218321
    ],
    "placeRotation": [
      [
        0.00639507454,
        -0.0427457057,
        0.9990655
      ],
      [
        0.0101508545,
        0.999037266,
        0.04267952
      ],
      [
        -0.999928057,
        0.00986843,
        0.006822823
      ]
    ],
    "placeTranslation": [
      0.2674666,
      0.202970043,
      -0.451960117
    ]
  },
  {
    "id": "005 tomato soup can(Clone)-7146",
    "pickRotation": [
      [
        -0.8424041,
        -0.09700616,
        -0.5300426
      ],
      [
        0.5379396,
        -0.208438233,
        -0.8168075
      ],
      [
        -0.0312457681,
        -0.9732129,
        0.227772668
      ]
    ],
    "pickTranslation": [
      0.0152210519,
      0.0982101,
      0.112394415
    ],
    "placeRotation": [
      [
        0.7476084,
        0.663876,
        0.0187176317
      ],
      [
        -0.049543187,
        0.02764284,
        0.998389363
      ],
      [
        0.6622893,
        -0.7473316,
        0.053556554
      ]
    ],
    "placeTranslation": [
      -0.282656074,
      -0.0153210349,
      -0.206610724
    ]
  },
  {
    "id": "002 masterchef can(Clone)-6600",
    "pickRotation": [
      [
        -0.107906386,
        -0.324469179,
        -0.9397213
      ],
      [
        0.9740265,
        0.154768944,
        -0.165284574
      ],
      [
        0.199069411,
        -0.9331486,
        0.299341023
      ]
    ],
    "pickTranslation": [
      0.0137221105,
      0.00140255876,
      0.129157335
    ],
    "placeRotation": [
      [
        0.9990696,
        0.00112840219,
        0.0431140848
      ],
      [
        -0.04304743,
        0.087485224,
        0.995235264
      ],
      [
        -0.002648829,
        -0.9961652,
        0.08745239
      ]
    ],
    "placeTranslation": [
      0.137566075,
      0.379630774,
      -0.6936872
    ]
  },
  {
    "id": "101 bread(Clone)-6552",
    "pickRotation": [
      [
        -0.81175226,
        -0.458122432,
        -0.362190664
      ],
      [
        0.446633458,
        -0.886579633,
        0.120395966
      ],
      [
        -0.376266956,
        -0.06403477,
        0.9242958
      ]
    ],
    "pickTranslation": [
      0.009858935,
      0.0377571881,
      -0.00325498
    ],
    "placeRotation": [
      [
        0.9625044,
        -0.248297721,
        -0.109240532
      ],
      [
        0.241320908,
        0.9676783,
        -0.07323182
      ],
      [
        0.123892993,
        0.0441239178,
        0.991314054
      ]
    ],
    "placeTranslation": [
      -0.4288379,
      0.3171756,
      0.6101863
    ]
  },
  {
    "id": "016 pear(Clone)-6528",
    "pickRotation": [
      [
        0.0231576227,
        -0.9321888,
        -0.36123094
      ],
      [
        0.450368017,
        0.332314461,
        -0.828695238
      ],
      [
        0.89254266,
        -0.14349623,
        0.427523643
      ]
    ],
    "pickTranslation": [
      0.0423363559,
      -0.004216082,
      0.0362016745
    ],
    "placeRotation": [
      [
        0.202617839,
        -0.13265039,
        -0.9702319
      ],
      [
        0.9654031,
        -0.1390165,
        0.2206158
      ],
      [
        -0.164143011,
        -0.9813655,
        0.09989387
      ]
    ],
    "placeTranslation": [
      -0.4852691,
      0.318963021,
      0.185886949
    ]
  },
  {
    "id": "103 toothpaste(Clone)-6564",
    "pickRotation": [
      [
        -0.0505216047,
        -0.0610611476,
        -0.9968546
      ],
      [
        -0.998722434,
        0.004157506,
        0.0503616035
      ],
      [
        0.00106929173,
        0.9981254,
        -0.06119318
      ]
    ],
    "pickTranslation": [
      0.00901815,
      0.0199051183,
      -0.03592702
    ],
    "placeRotation": [
      [
        0.105400994,
        0.9821602,
        -0.155730441
      ],
      [
        0.09729463,
        -0.166036561,
        -0.9813081
      ],
      [
        -0.9896587,
        0.0882791,
        -0.113059327
      ]
    ],
    "placeTranslation": [
      -0.32562837,
      0.598811567,
      0.402291566
    ]
  },
  {
    "id": "018 plum(Clone)-6612",
    "pickRotation": [
      [
        0.882018,
        -0.31414178,
        -0.3512252
      ],
      [
        -0.155007526,
        -0.8973046,
        0.413300157
      ],
      [
        -0.444990844,
        -0.310095638,
        -0.8401332
      ]
    ],
    "pickTranslation": [
      0.005819185,
      0.0278168358,
      0.0137705244
    ],
    "placeRotation": [
      [
        -0.748460233,
        0.185131252,
        0.6368153
      ],
      [
        0.4752126,
        0.819506943,
        0.3202834
      ],
      [
        -0.462580055,
        0.542342067,
        -0.701344967
      ]
    ],
    "placeTranslation": [
      0.00298712845,
      0.70557636,
      0.0285830442
    ]
  },
  {
    "id": "014 lemon(Clone)-6624",
    "pickRotation": [
      [
        -0.0453419834,
        -0.64209646,
        0.7652818
      ],
      [
        0.236860678,
        -0.7511347,
        -0.6161929
      ],
      [
        0.970485,
        0.153325766,
        0.186145335
      ]
    ],
    "pickTranslation": [
      0.0217441637,
      0.01928954,
      0.03896345
    ],
    "placeRotation": [
      [
        -0.127305686,
        0.08754443,
        -0.9879925
      ],
      [
        0.5321115,
        0.846649647,
        0.00645615533
      ],
      [
        0.837048769,
        -0.5249003,
        -0.154366717
      ]
    ],
    "placeTranslation": [
      -0.4475343,
      0.5744804,
      -0.3270414
    ]
  },
  {
    "id": "007 tuna fish can(Clone)-6810",
    "pickRotation": [
      [
        -0.766062,
        -0.12461108,
        -0.630572
      ],
      [
        0.6187549,
        0.122670077,
        -0.7759474
      ],
      [
        0.174043968,
        -0.9845934,
        -0.0168691669
      ]
    ],
    "pickTranslation": [
      0.0284066051,
      -0.0123034436,
      0.03278776
    ],
    "placeRotation": [
      [
        0.9628021,
        -0.269913644,
        0.0125963427
      ],
      [
        -0.0119441859,
        0.00405852962,
        0.9999204
      ],
      [
        -0.2699433,
        -0.962875962,
        0.000683662249
      ]
    ],
    "placeTranslation": [
      -0.6514533,
      0.5192128,
      -0.808203638
    ]
  },
  {
    "id": "011 banana(Clone)-6636",
    "pickRotation": [
      [
        -0.92494756,
        -0.143455058,
        -0.351984
      ],
      [
        0.328347564,
        0.164915726,
        -0.930048764
      ],
      [
        0.191467881,
        -0.9758194,
        -0.105435282
      ]
    ],
    "pickTranslation": [
      0.0159178954,
      0.00224618823,
      0.01651058
    ],
    "placeRotation": [
      [
        0.9089284,
        0.345208317,
        -0.233838484
      ],
      [
        0.283745676,
        -0.101181358,
        0.9535464
      ],
      [
        0.305512071,
        -0.933056,
        -0.189917967
      ]
    ],
    "placeTranslation": [
      -0.24754937,
      0.718270063,
      0.2759172
    ]
  },
  {
    "id": "057 racquetball(Clone)-6734",
    "pickRotation": [
      [
        -0.802025139,
        -0.0420489125,
        -0.595808268
      ],
      [
        0.0413043648,
        -0.9990354,
        0.0149061559
      ],
      [
        -0.595860362,
        -0.0126543706,
        0.80298835
      ]
    ],
    "pickTranslation": [
      0.00620297249,
      -0.118747979,
      0.01867522
    ],
    "placeRotation": [
      [
        0.9518447,
        0.117358021,
        0.283229023
      ],
      [
        -0.07466656,
        0.984754562,
        -0.157109186
      ],
      [
        -0.2973491,
        0.128395811,
        0.9460962
      ]
    ],
    "placeTranslation": [
      -0.222638518,
      1.70107424,
      -0.289415121
    ]
  },
  {
    "id": "015 peach(Clone)-6786",
    "pickRotation": [
      [
        -0.04848101,
        0.0899749249,
        0.9947633
      ],
      [
        -0.997184932,
        0.0526733622,
        -0.0533632636
      ],
      [
        -0.0571988858,
        -0.994550169,
        0.0871679857
      ]
    ],
    "pickTranslation": [
      -0.007944362,
      0.008365189,
      0.0470390767
    ],
    "placeRotation": [
      [
        -0.153882161,
        0.952660441,
        0.262218
      ],
      [
        -0.205304369,
        -0.290414244,
        0.9346174
      ],
      [
        0.9665249,
        0.08998645,
        0.240274936
      ]
    ],
    "placeTranslation": [
      0.44134587,
      0.8535099,
      -0.1306596
    ]
  },
  {
    "id": "058 golf ball(Clone)-6774",
    "pickRotation": [
      [
        -0.5057748,
        -0.118467547,
        -0.8544924
      ],
      [
        0.757054031,
        -0.535849869,
        -0.373810232
      ],
      [
        -0.4135953,
        -0.835960746,
        0.360705674
      ]
    ],
    "pickTranslation": [
      0.0097041,
      -0.007558182,
      0.0217923671
    ],
    "placeRotation": [
      [
        0.685378253,
        -0.5841412,
        0.434782416
      ],
      [
        0.2016637,
        0.7259832,
        0.6574801
      ],
      [
        -0.699705958,
        -0.362942725,
        0.6153732
      ]
    ],
    "placeTranslation": [
      -0.0106470659,
      0.8275863,
      -0.224385381
    ]
  },
  {
    "id": "013 apple(Clone)-6694",
    "pickRotation": [
      [
        -0.02074371,
        -0.00209611072,
        -0.9997826
      ],
      [
        0.986817,
        -0.16058217,
        -0.0201380271
      ],
      [
        -0.160505056,
        -0.9870202,
        0.005399548
      ]
    ],
    "pickTranslation": [
      0.000143687692,
      -0.00386229577,
      0.0469453037
    ],
    "placeRotation": [
      [
        0.115960747,
        -0.982143641,
        0.148145393
      ],
      [
        0.130559936,
        0.162929609,
        0.9779612
      ],
      [
        -0.9846356,
        -0.09406327,
        0.14712204
      ]
    ],
    "placeTranslation": [
      0.280154943,
      0.7140562,
      0.3346666
    ]
  },
  {
    "id": "017 orange(Clone)-6762",
    "pickRotation": [
      [
        -0.952643633,
        0.2515086,
        -0.17091997
      ],
      [
        -0.247582719,
        -0.315160036,
        0.9161752
      ],
      [
        0.1765588,
        0.9151053,
        0.362504363
      ]
    ],
    "pickTranslation": [
      0.00306177558,
      -0.0153345652,
      0.0225586984
    ],
    "placeRotation": [
      [
        0.962567747,
        0.174020648,
        -0.2077983
      ],
      [
        -0.244999543,
        0.230728686,
        -0.941668451
      ],
      [
        -0.115924709,
        0.957330167,
        0.264726967
      ]
    ],
    "placeTranslation": [
      -0.736635864,
      1.12840033,
      -0.355630726
    ]
  }
]