[
  {
    "id": "010 potted meat can(Clone)-24570",
    "pickRotation": [
      [
        0.01523333,
        0.0542918,
        -0.998408854
      ],
      [
        0.9993009,
        -0.0349207744,
        0.0133480085
      ],
      [
        -0.0341405235,
        -0.997914255,
        -0.0547858067
      ]
    ],
    "pickTranslation": [
      0.03710005,
      -0.0280745663,
      0.07580421
    ],
    "placeRotation": [
      [
        -0.0968373045,
        -0.9928845,
        -0.06930328
      ],
      [
        0.0169828683,
        -0.071268715,
        0.997312546
      ],
      [
        -0.995155334,
        0.09540008,
        0.0237634964
      ]
    ],
    "placeTranslation": [
      -0.888061047,
      0.0648435652,
      0.474105716
    ]
  },
  {
    "id": "010 potted meat can(Clone)-24582",
    "pickRotation": [
      [
        -0.0646708757,
        0.00589361135,
        -0.9978892
      ],
      [
        0.993689537,
        -0.09145513,
        -0.06493884
      ],
      [
        -0.0916448161,
        -0.9957918,
        5.806324E-05
      ]
    ],
    "pickTranslation": [
      0.0285970625,
      -0.0286190733,
      0.08091138
    ],
    "placeRotation": [
      [
        -0.0535191372,
        -0.9979605,
        -0.03479331
      ],
      [
        0.0231239144,
        -0.0360724963,
        0.9990816
      ],
      [
        -0.998299062,
        0.05266543,
        0.0250073224
      ]
    ],
    "placeTranslation": [
      -0.8952791,
      0.5256352,
      0.524784267
    ]
  },
  {
    "id": "005 tomato soup can(Clone)-24510",
    "pickRotation": [
      [
        -0.8600898,
        0.02246557,
        -0.5096478
      ],
      [
        0.5092662,
        -0.0207261816,
        -0.86035943
      ],
      [
        -0.0298915189,
        -0.999532759,
        0.00638542138
      ]
    ],
    "pickTranslation": [
      0.009749351,
      0.08515023,
      0.09906649
    ],
    "placeRotation": [
      [
        0.723066,
        -0.687214851,
        -0.0700814649
      ],
      [
        0.02762298,
        -0.0726067647,
        0.996978045
      ],
      [
        -0.690226555,
        -0.722816765,
        -0.03351656
      ]
    ],
    "placeTranslation": [
      -1.14958441,
      0.1308018,
      0.676443458
    ]
  },
  {
    "id": "002 masterchef can(Clone)-24450",
    "pickRotation": [
      [
        -0.767540336,
        -1.22010988E-05,
        -0.6410006
      ],
      [
        0.6408645,
        -0.0206224155,
        -0.767376959
      ],
      [
        -0.0132096186,
        -0.9997873,
        0.0158363562
      ]
    ],
    "pickTranslation": [
      0.022448238,
      0.000767498161,
      0.155310482
    ],
    "placeRotation": [
      [
        0.6565041,
        -0.744383633,
        -0.122046553
      ],
      [
        0.0568623655,
        -0.112499341,
        0.992023468
      ],
      [
        -0.752176166,
        -0.6582073,
        -0.0315288641
      ]
    ],
    "placeTranslation": [
      -0.8431667,
      0.6736449,
      0.137793258
    ]
  },
  {
    "id": "005 tomato soup can(Clone)-24546",
    "pickRotation": [
      [
        -0.5758967,
        -0.23769401,
        -0.7822049
      ],
      [
        0.8157202,
        -0.103573844,
        -0.5690985
      ],
      [
        0.0542553328,
        -0.965802252,
        0.253539622
      ]
    ],
    "pickTranslation": [
      0.011927763,
      0.07819744,
      0.09959346
    ],
    "placeRotation": [
      [
        0.442816526,
        -0.888619542,
        -0.119452149
      ],
      [
        -0.00166828441,
        -0.134042442,
        0.9909742
      ],
      [
        -0.896610737,
        -0.438620478,
        -0.06083868
      ]
    ],
    "placeTranslation": [
      -0.9992826,
      0.178033009,
      0.229331359
    ]
  },
  {
    "id": "002 masterchef can(Clone)-24364",
    "pickRotation": [
      [
        -0.4589583,
        -0.15411599,
        -0.874988854
      ],
      [
        0.8846252,
        -0.1706474,
        -0.4339559
      ],
      [
        -0.08243503,
        -0.973204851,
        0.214654922
      ]
    ],
    "pickTranslation": [
      0.0272768028,
      -0.003622316,
      0.1439268
    ],
    "placeRotation": [
      [
        0.356606,
        -0.933717132,
        -0.03169229
      ],
      [
        -0.00583242532,
        -0.03614683,
        0.999329448
      ],
      [
        -0.934236646,
        -0.356182039,
        -0.018336013
      ]
    ],
    "placeTranslation": [
      -0.852644444,
      0.697735965,
      -0.4390982
    ]
  },
  {
    "id": "021 bleach cleanser(Clone)-24558",
    "pickRotation": [
      [
        0.754045546,
        0.176418826,
        0.6326861
      ],
      [
        -0.6512098,
        0.326454818,
        0.685093462
      ],
      [
        -0.08568003,
        -0.928603053,
        0.361047477
      ]
    ],
    "pickTranslation": [
      0.004721421,
      0.004546314,
      0.241748363
    ],
    "placeRotation": [
      [
        -0.996910632,
        0.03256795,
        -0.07147369
      ],
      [
        -0.0702749,
        0.03657702,
        0.996856868
      ],
      [
        0.0350798555,
        0.9988,
        -0.03417531
      ]
    ],
    "placeTranslation": [
      -0.282563627,
      0.079694815,
      0.01950843
    ]
  },
  {
    "id": "002 masterchef can(Clone)-24498",
    "pickRotation": [
      [
        -0.5255176,
        -0.09355651,
        -0.8456231
      ],
      [
        0.8507822,
        -0.05680196,
        -0.5224395
      ],
      [
        0.0008445615,
        -0.993992269,
        0.109446652
      ]
    ],
    "pickTranslation": [
      0.0294216741,
      -0.0100125214,
      0.1345966
    ],
    "placeRotation": [
      [
        0.2917592,
        -0.9529363,
        -0.08239522
      ],
      [
        -0.07663208,
        -0.109154463,
        0.9910665
      ],
      [
        -0.953417063,
        -0.282838643,
        -0.104872316
      ]
    ],
    "placeTranslation": [
      -0.182738662,
      0.139745772,
      0.514231265
    ]
  },
  {
    "id": "004 sugar box(Clone)-24434",
    "pickRotation": [
      [
        -0.984371066,
        -0.07803027,
        0.1578761
      ],
      [
        -0.146492586,
        -0.134745121,
        -0.9799917
      ],
      [
        0.09774205,
        -0.987803161,
        0.121208347
      ]
    ],
    "pickTranslation": [
      0.009435939,
      -0.004981533,
      0.165908143
    ],
    "placeRotation": [
      [
        0.9915995,
        0.128056929,
        0.01821693
      ],
      [
        -0.014265608,
        -0.0317058042,
        0.99939543
      ],
      [
        0.128557086,
        -0.9912599,
        -0.0296126511
      ]
    ],
    "placeTranslation": [
      -0.269129783,
      0.436037332,
      -0.8097658
    ]
  },
  {
    "id": "013 apple(Clone)-24352",
    "pickRotation": [
      [
        -0.2907989,
        -0.0616071373,
        -0.954798758
      ],
      [
        0.9535394,
        0.06345596,
        -0.294509768
      ],
      [
        0.0787315741,
        -0.9960813,
        0.0402919054
      ]
    ],
    "pickTranslation": [
      0.006849707,
      -0.00748146325,
      0.07122677
    ],
    "placeRotation": [
      [
        0.0159285683,
        -0.9960831,
        -0.0869758949
      ],
      [
        -0.06495447,
        -0.08783402,
        0.994015157
      ],
      [
        -0.9977611,
        -0.0101837795,
        -0.0660991147
      ]
    ],
    "placeTranslation": [
      0.0500323661,
      -0.00459402055,
      0.158468917
    ]
  },
  {
    "id": "100 half egg carton(Clone)-24642",
    "pickRotation": [
      [
        0.0516323224,
        0.08369968,
        0.995152533
      ],
      [
        -0.0411651246,
        -0.995456338,
        0.08586104
      ],
      [
        0.9978174,
        -0.0453987829,
        -0.0479522161
      ]
    ],
    "pickTranslation": [
      -0.07499266,
      0.0356794745,
      0.00190587319
    ],
    "placeRotation": [
      [
        -0.9931725,
        -0.116042227,
        -0.011941731
      ],
      [
        -0.115059257,
        0.991314352,
        -0.06369588
      ],
      [
        0.0192294214,
        -0.06188699,
        -0.997897863
      ]
    ],
    "placeTranslation": [
      0.6700894,
      0.240543932,
      -0.3580544
    ]
  },
  {
    "id": "011 banana(Clone)-24376",
    "pickRotation": [
      [
        0.5976349,
        0.0328909829,
        -0.801093459
      ],
      [
        0.789709747,
        -0.196785346,
        0.581062853
      ],
      [
        -0.138531715,
        -0.979894757,
        -0.143580109
      ]
    ],
    "pickTranslation": [
      0.01691161,
      0.0127521027,
      0.0352304243
    ],
    "placeRotation": [
      [
        0.5686854,
        -0.801053464,
        -0.186842963
      ],
      [
        0.266382277,
        -0.0355551466,
        0.9632115
      ],
      [
        -0.77822715,
        -0.597535968,
        0.193166748
      ]
    ],
    "placeTranslation": [
      0.7558787,
      0.538491368,
      0.223465264
    ]
  },
  {
    "id": "017 orange(Clone)-24474",
    "pickRotation": [
      [
        -0.03605103,
        0.9897028,
        0.138523564
      ],
      [
        -0.4368986,
        -0.1402741,
        0.888505936
      ],
      [
        0.8987881,
        -0.0284891985,
        0.437456757
      ]
    ],
    "pickTranslation": [
      -0.032639388,
      -0.0162514467,
      0.0346576646
    ],
    "placeRotation": [
      [
        0.338056326,
        0.687628,
        -0.642561853
      ],
      [
        -0.92923665,
        0.35206148,
        -0.112124622
      ],
      [
        0.149121255,
        0.6349965,
        0.7579857
      ]
    ],
    "placeTranslation": [
      0.314325452,
      0.789660454,
      0.9055788
    ]
  },
  {
    "id": "017 orange(Clone)-24534",
    "pickRotation": [
      [
        -0.60913986,
        -0.78887254,
        -0.08141717
      ],
      [
        -0.042627167,
        -0.0699449852,
        0.996639669
      ],
      [
        -0.7919164,
        0.6105635,
        0.008978877
      ]
    ],
    "pickTranslation": [
      0.0356603265,
      -0.0122019853,
      0.008602808
    ],
    "placeRotation": [
      [
        0.5794198,
        0.333462983,
        0.7436902
      ],
      [
        0.733556,
        0.184300885,
        -0.6541627
      ],
      [
        -0.3552018,
        0.9245732,
        -0.137826174
      ]
    ],
    "placeTranslation": [
      0.02616538,
      0.5843709,
      -0.6459701
    ]
  },
  {
    "id": "013 apple(Clone)-24486",
    "pickRotation": [
      [
        -0.247736424,
        -0.158516556,
        -0.955771446
      ],
      [
        0.95075196,
        0.149896741,
        -0.271296054
      ],
      [
        0.186271951,
        -0.975911558,
        0.113575056
      ]
    ],
    "pickTranslation": [
      -0.007913643,
      0.0022200942,
      0.08361876
    ],
    "placeRotation": [
      [
        -0.05011516,
        -0.9983052,
        -0.029585246
      ],
      [
        -0.139545664,
        -0.02233282,
        0.98996377
      ],
      [
        -0.9889467,
        0.0537406839,
        -0.138189942
      ]
    ],
    "placeTranslation": [
      0.191304028,
      0.5615823,
      -0.2576573
    ]
  },
  {
    "id": "017 orange(Clone)-24630",
    "pickRotation": [
      [
        -0.8646692,
        0.499240935,
        -0.05572922
      ],
      [
        0.0107431663,
        0.1292913,
        0.9915485
      ],
      [
        0.5022269,
        0.8567627,
        -0.117157631
      ]
    ],
    "pickTranslation": [
      -0.0124829914,
      -0.0298543181,
      8.17291439E-05
    ],
    "placeRotation": [
      [
        0.814794838,
        0.3974111,
        -0.422106415
      ],
      [
        -0.50710547,
        0.13566649,
        -0.851139665
      ],
      [
        -0.280986667,
        0.9075566,
        0.312069684
      ]
    ],
    "placeTranslation": [
      0.06587001,
      1.04002988,
      0.39687705
    ]
  },
  {
    "id": "013 apple(Clone)-24606",
    "pickRotation": [
      [
        -0.774411,
        -0.131317854,
        -0.618904769
      ],
      [
        0.6265551,
        -0.0233608019,
        -0.7790269
      ],
      [
        0.08784203,
        -0.991065,
        0.100368731
      ]
    ],
    "pickTranslation": [
      0.01667358,
      0.0138786063,
      0.0677593
    ],
    "placeRotation": [
      [
        0.6297683,
        -0.7742437,
        0.06275771
      ],
      [
        0.02952737,
        0.104594156,
        0.99407655
      ],
      [
        -0.776221633,
        -0.624184847,
        0.08873146
      ]
    ],
    "placeTranslation": [
      0.5874639,
      0.493084371,
      -0.6037092
    ]
  },
  {
    "id": "016 pear(Clone)-24594",
    "pickRotation": [
      [
        -0.755116165,
        -0.177060679,
        -0.6312282
      ],
      [
        0.634453535,
        0.04515576,
        -0.771640837
      ],
      [
        0.165130854,
        -0.983163536,
        0.0782389343
      ]
    ],
    "pickTranslation": [
      0.0375587158,
      0.009653684,
      0.0636105537
    ],
    "placeRotation": [
      [
        0.838447154,
        -0.443915367,
        -0.316141546
      ],
      [
        0.2657793,
        -0.1733675,
        0.948317
      ],
      [
        -0.475781143,
        -0.8791375,
        -0.0273759738
      ]
    ],
    "placeTranslation": [
      0.4385202,
      0.737071753,
      -0.510818
    ]
  },
  {
    "id": "015 peach(Clone)-24618",
    "pickRotation": [
      [
        -0.336999178,
        0.127572343,
        0.9328219
      ],
      [
        -0.9412211,
        -0.069974415,
        -0.330463856
      ],
      [
        0.0231156237,
        -0.989357769,
        0.1436551
      ]
    ],
    "pickTranslation": [
      -0.00393021945,
      0.0190609284,
      0.0487198457
    ],
    "placeRotation": [
      [
        0.716016054,
        0.698058665,
        -0.005925859
      ],
      [
        0.0564420074,
        -0.04942883,
        0.9971816
      ],
      [
        0.6957984,
        -0.714332461,
        -0.07479167
      ]
    ],
    "placeTranslation": [
      0.07328646,
      0.754074,
      0.1592469
    ]
  },
  {
    "id": "058 golf ball(Clone)-24462",
    "pickRotation": [
      [
        -0.7113714,
        -0.196416736,
        -0.674812
      ],
      [
        0.6661937,
        -0.494346261,
        -0.5583975
      ],
      [
        -0.22391215,
        -0.8467835,
        0.4825154
      ]
    ],
    "pickTranslation": [
      0.008906419,
      -0.00648974255,
      0.0300959721
    ],
    "placeRotation": [
      [
        0.693706155,
        -0.6273494,
        0.3538425
      ],
      [
        -0.0008387556,
        0.490567774,
        0.8714026
      ],
      [
        -0.72025764,
        -0.604794145,
        0.339783728
      ]
    ],
    "placeTranslation": [
      0.493346184,
      0.8676307,
      -1.00513315
    ]
  },
  {
    "id": "012 strawberry(Clone)-24340",
    "pickRotation": [
      [
        0.3141578,
        -0.503253162,
        -0.80501
      ],
      [
        0.0341254137,
        -0.8414065,
        0.5393241
      ],
      [
        -0.948757231,
        -0.196904182,
        -0.247160718
      ]
    ],
    "pickTranslation": [
      0.0234797373,
      0.02777076,
      0.006425226
    ],
    "placeRotation": [
      [
        -0.418988377,
        0.115105152,
        0.9006662
      ],
      [
        0.421461,
        0.903255165,
        0.08062691
      ],
      [
        -0.804250836,
        0.4133774,
        -0.426965743
      ]
    ],
    "placeTranslation": [
      0.3773854,
      0.826122761,
      -0.753438234
    ]
  },
  {
    "id": "018 plum(Clone)-24522",
    "pickRotation": [
      [
        0.5949535,
        0.587513566,
        -0.5485054
      ],
      [
        -0.7802022,
        0.258129,
        -0.5697841
      ],
      [
        -0.193170726,
        0.766940236,
        0.6119541
      ]
    ],
    "pickTranslation": [
      -0.003763284,
      -0.00256255385,
      0.00123740581
    ],
    "placeRotation": [
      [
        -0.676705837,
        0.4830234,
        0.555659652
      ],
      [
        -0.700513065,
        -0.190117314,
        -0.687849462
      ],
      [
        -0.226606876,
        -0.854718566,
        0.4670177
      ]
    ],
    "placeTranslation": [
      0.626513839,
      1.06416607,
      -0.09882646
    ]
  }
]